[{"type": "var", "name": "copyright", "content": {"type": "text", "content": "Copyright 1993 Francis Borceux"}, "pattern": ".{0,5000}"}, {"type": "text", "content": "\n\n      You may freely use, modify, and/or distribute each of the files in this package without limitation. The\n         package consists of the following files:\n        README\n        compatibility/OldDiagram\n        compatibility/OldMaxiDiagram\n        compatibility/OldMicroDiagram\n        compatibility/OldMiniDiagram\n        compatibility/OldMultipleArrows\n        diagram/Diagram\n        diagram/MaxiDiagram\n        diagram/MicroDiagram\n        diagram/MiniDiagram\n        diagram/MultipleArrows\n        user-guides/Diagram_Mode_d_Emploi\n        user-guides/Diagram_Read_Me\n      Of course no support is guaranteed, but the author will attempt to assist with problems. Current email address:\n        francis dot borceux at uclouvain dot be."}]